{
  "_class": "oval",
  "booleanOperation": -1,
  "do_objectID": "E87F3723-DB0B-4B82-939E-01DF386F009C",
  "edited": false,
  "exportOptions": {
    "_class": "exportOptions",
    "do_objectID": "43BF35B2-0582-43FD-BC17-37C480DD72D9",
    "exportFormats": [
    ],
    "includedLayerIds": [
    ],
    "layerOptions": 0,
    "shouldTrim": false
  },
  "frame": {
    "_class": "rect",
    "constrainProportions": false,
    "do_objectID": "58AD7C52-1037-471F-9FC9-17F8A14D9AF9",
    "height": 5,
    "width": 5,
    "x": 0,
    "y": 0
  },
  "isClosed": true,
  "isFlippedHorizontal": false,
  "isFlippedVertical": false,
  "isLocked": false,
  "isVisible": true,
  "layerListExpandedType": 0,
  "name": "Path",
  "nameIsFixed": false,
  "path": {
    "_class": "path",
    "isClosed": true,
    "pointRadiusBehaviour": 1,
    "points": [
      {
        "_class": "curvePoint",
        "cornerRadius": 0,
        "curveFrom": "{0.77614237490000004, 1}",
        "curveMode": 2,
        "curveTo": "{0.22385762510000001, 1}",
        "hasCurveFrom": true,
        "hasCurveTo": true,
        "point": "{0.5, 1}"
      },
      {
        "_class": "curvePoint",
        "cornerRadius": 0,
        "curveFrom": "{1, 0.22385762510000001}",
        "curveMode": 2,
        "curveTo": "{1, 0.77614237490000004}",
        "hasCurveFrom": true,
        "hasCurveTo": true,
        "point": "{1, 0.5}"
      },
      {
        "_class": "curvePoint",
        "cornerRadius": 0,
        "curveFrom": "{0.22385762510000001, 0}",
        "curveMode": 2,
        "curveTo": "{0.77614237490000004, 0}",
        "hasCurveFrom": true,
        "hasCurveTo": true,
        "point": "{0.5, 0}"
      },
      {
        "_class": "curvePoint",
        "cornerRadius": 0,
        "curveFrom": "{0, 0.77614237490000004}",
        "curveMode": 2,
        "curveTo": "{0, 0.22385762510000001}",
        "hasCurveFrom": true,
        "hasCurveTo": true,
        "point": "{0, 0.5}"
      }
    ]
  },
  "pointRadiusBehaviour": 1,
  "points": [
    {
      "_class": "curvePoint",
      "cornerRadius": 0,
      "curveFrom": "{0.77614237490000004, 1}",
      "curveMode": 2,
      "curveTo": "{0.22385762510000001, 1}",
      "hasCurveFrom": true,
      "hasCurveTo": true,
      "point": "{0.5, 1}"
    },
    {
      "_class": "curvePoint",
      "cornerRadius": 0,
      "curveFrom": "{1, 0.22385762510000001}",
      "curveMode": 2,
      "curveTo": "{1, 0.77614237490000004}",
      "hasCurveFrom": true,
      "hasCurveTo": true,
      "point": "{1, 0.5}"
    },
    {
      "_class": "curvePoint",
      "cornerRadius": 0,
      "curveFrom": "{0.22385762510000001, 0}",
      "curveMode": 2,
      "curveTo": "{0.77614237490000004, 0}",
      "hasCurveFrom": true,
      "hasCurveTo": true,
      "point": "{0.5, 0}"
    },
    {
      "_class": "curvePoint",
      "cornerRadius": 0,
      "curveFrom": "{0, 0.77614237490000004}",
      "curveMode": 2,
      "curveTo": "{0, 0.22385762510000001}",
      "hasCurveFrom": true,
      "hasCurveTo": true,
      "point": "{0, 0.5}"
    }
  ],
  "resizingConstraint": 63,
  "resizingType": 0,
  "rotation": 0,
  "shouldBreakMaskChain": false
}